{"repository":"https://github.com/ui-router/quickstart-ng2","dockerfilePath":"Dockerfile","startTime":1672807026141,"clone":{"stdout":"","stderr":"Cloning into '/tmp/dinghy-analysis/ui-router/quickstart-ng2'...\n","error":null,"commit":"8d3f8c417033480fa1de69252f713206e8cf8640"},"originalBuild":{"startTimestamp":1672807027016,"endTimestamp":1672807048946,"error":{"code":1,"killed":false,"signal":null,"cmd":"docker build --no-cache --force-rm -t quickstart-ng2:latest -f /tmp/dinghy-analysis/ui-router/quickstart-ng2/Dockerfile ."},"stdout":"Sending build context to Docker daemon  222.7kB\r\r\nStep 1/9 : FROM node:latest\nlatest: Pulling from library/node\n32de3c850997: Already exists\nfa1d4c8d85a4: Already exists\nc796299bbbdd: Already exists\n81283a9569ad: Already exists\n60b38700e7fb: Already exists\n9537c7a3988e: Already exists\ndfc2ed565c15: Pulling fs layer\nb65dd9eadf26: Pulling fs layer\nc46cc3bcdf59: Pulling fs layer\nc46cc3bcdf59: Verifying Checksum\nb65dd9eadf26: Verifying Checksum\nb65dd9eadf26: Download complete\ndfc2ed565c15: Verifying Checksum\ndfc2ed565c15: Download complete\ndfc2ed565c15: Pull complete\nb65dd9eadf26: Pull complete\nc46cc3bcdf59: Pull complete\nDigest: sha256:d5222e1ebd7dd7e9683f47a8861a4711cb4407a4830cbe04a582ca4986245700\nStatus: Downloaded newer image for node:latest\n ---> 548714e444f4\nStep 2/9 : RUN mkdir -p /quickstart /home/nodejs &&     groupadd -r nodejs &&     useradd -r -g nodejs -d /home/nodejs -s /sbin/nologin nodejs &&     chown -R nodejs:nodejs /home/nodejs\n ---> Running in a90b426e5929\nRemoving intermediate container a90b426e5929\n ---> 58f4774843b9\nStep 3/9 : WORKDIR /quickstart\n ---> Running in eb0b3140fc0b\nRemoving intermediate container eb0b3140fc0b\n ---> b84209f0204f\nStep 4/9 : COPY package.json typings.json /quickstart/\n","stderr":"COPY failed: file not found in build context or excluded by .dockerignore: stat typings.json: file does not exist\n"},"endTime":1672807049021}