{
  "startTime": 1674237087888,
  "endTime": 1674237087997,
  "originalSmells": [
    {
      "rule": "curlUseFlagF",
      "position": {
        "lineStart": 6,
        "lineEnd": 6,
        "columnStart": 4,
        "columnEnd": 102
      }
    },
    {
      "rule": "curlUseFlagF",
      "position": {
        "lineStart": 11,
        "lineEnd": 11,
        "columnStart": 4,
        "columnEnd": 49
      }
    },
    {
      "rule": "aptGetInstallUseNoRec",
      "position": {
        "lineStart": 2,
        "lineEnd": 2,
        "columnStart": 5,
        "columnEnd": 80
      }
    },
    {
      "rule": "aptGetInstallUseNoRec",
      "position": {
        "lineStart": 12,
        "lineEnd": 12,
        "columnStart": 4,
        "columnEnd": 45
      }
    },
    {
      "rule": "aptGetUpdatePrecedesInstall",
      "position": {
        "lineStart": 12,
        "lineEnd": 12,
        "columnStart": 4,
        "columnEnd": 45
      }
    },
    {
      "rule": "aptGetInstallThenRemoveAptLists",
      "position": {
        "lineStart": 12,
        "lineEnd": 12,
        "columnStart": 4,
        "columnEnd": 45
      }
    }
  ],
  "repairedSmells": [
    {
      "rule": "aptGetUpdatePrecedesInstall",
      "position": {
        "lineStart": 12,
        "lineEnd": 12,
        "columnStart": 4,
        "columnEnd": 69
      }
    }
  ],
  "repairedDockerfile": "FROM ruby:2.3.3\nRUN apt-get update \\\n  && apt-get install --no-install-recommends -y postgresql postgresql-contrib libpq-dev curl bash git jq \\\n  && apt-get clean \\\n  && rm -rf /var/lib/apt/lists/* /tmp/* /var/tmp/*\n#\nRUN curl -f -o /usr/local/bin/gosu -sSL \"https://github.com/tianon/gosu/releases/download/1.7/gosu-amd64\" && \\\n    chmod +x /usr/local/bin/gosu\nWORKDIR /opt\nRUN git clone --depth=1 https://github.com/FarmBot/Farmbot-Web-API\nRUN cd Farmbot-Web-API && bundle install\nRUN curl -f -sL https://deb.nodesource.com/setup_7.x | bash\nRUN apt-get install --no-install-recommends -y nodejs build-essential && rm -rf /var/lib/apt/lists/*;\nWORKDIR /opt/Farmbot-Web-API\n# ./install_fronted error · Issue #199 · FarmBot/farmbot-web-frontend\n# https://github.com/FarmBot/farmbot-web-frontend/issues/199\nRUN ./install_frontend.sh\nADD database.yml config/\nADD start.sh /start.sh\nRUN chmod +x /start.sh\n"
}