{"repository":"https://github.com/crafatar/crafatar","dockerfilePath":"Dockerfile","startTime":1672816916747,"clone":{"stdout":"","stderr":"Cloning into '/tmp/dinghy-analysis/crafatar/crafatar'...\n","error":null,"commit":"fb4d24de6bcf1235f0fe876dfa76e43e7eb42fd8"},"originalBuild":{"startTimestamp":1672816917641,"endTimestamp":1672816934261,"error":{"code":1,"killed":false,"signal":null,"cmd":"docker build --no-cache --force-rm -t crafatar:latest -f /tmp/dinghy-analysis/crafatar/crafatar/Dockerfile ."},"stdout":"Sending build context to Docker daemon  481.3kB\r\r\nStep 1/26 : FROM node:12-alpine AS builder\n12-alpine: Pulling from library/node\ndf9b9388f04a: Already exists\n3bf6d7380205: Pulling fs layer\n7939e601ee5e: Pulling fs layer\n31f0fb9de071: Pulling fs layer\n31f0fb9de071: Verifying Checksum\n31f0fb9de071: Download complete\n7939e601ee5e: Verifying Checksum\n7939e601ee5e: Download complete\n3bf6d7380205: Verifying Checksum\n3bf6d7380205: Download complete\n3bf6d7380205: Pull complete\n7939e601ee5e: Pull complete\n31f0fb9de071: Pull complete\nDigest: sha256:d4b15b3d48f42059a15bd659be60afe21762aae9d6cbea6f124440895c27db68\nStatus: Downloaded newer image for node:12-alpine\n ---> bb6d28039b8c\nStep 2/26 : RUN apk --no-cache add git python build-base redis cairo-dev pango-dev jpeg-dev giflib-dev\n ---> Running in 09203723a1a0\nfetch https://dl-cdn.alpinelinux.org/alpine/v3.15/main/x86_64/APKINDEX.tar.gz\nfetch https://dl-cdn.alpinelinux.org/alpine/v3.15/community/x86_64/APKINDEX.tar.gz\n\u001b[91mERROR: unable to select packages:\n\u001b[0m  python (no such package):\n    required by: world[python]\nRemoving intermediate container 09203723a1a0\n","stderr":"The command '/bin/sh -c apk --no-cache add git python build-base redis cairo-dev pango-dev jpeg-dev giflib-dev' returned a non-zero code: 1\n"},"endTime":1672816934330}