{
  "id": 351639424,
  "node_id": "MDEwOlJlcG9zaXRvcnkzNTE2Mzk0MjQ=",
  "name": "rustybam",
  "full_name": "mrvollger/rustybam",
  "private": false,
  "owner": {
    "login": "mrvollger",
    "id": 6935283,
    "node_id": "MDQ6VXNlcjY5MzUyODM=",
    "avatar_url": "https://avatars.githubusercontent.com/u/6935283?v=4",
    "gravatar_id": "",
    "url": "https://api.github.com/users/mrvollger",
    "html_url": "https://github.com/mrvollger",
    "followers_url": "https://api.github.com/users/mrvollger/followers",
    "following_url": "https://api.github.com/users/mrvollger/following{/other_user}",
    "gists_url": "https://api.github.com/users/mrvollger/gists{/gist_id}",
    "starred_url": "https://api.github.com/users/mrvollger/starred{/owner}{/repo}",
    "subscriptions_url": "https://api.github.com/users/mrvollger/subscriptions",
    "organizations_url": "https://api.github.com/users/mrvollger/orgs",
    "repos_url": "https://api.github.com/users/mrvollger/repos",
    "events_url": "https://api.github.com/users/mrvollger/events{/privacy}",
    "received_events_url": "https://api.github.com/users/mrvollger/received_events",
    "type": "User",
    "site_admin": false
  },
  "html_url": "https://github.com/mrvollger/rustybam",
  "description": "bioinformatics toolkit in rust",
  "fork": false,
  "url": "https://api.github.com/repos/mrvollger/rustybam",
  "forks_url": "https://api.github.com/repos/mrvollger/rustybam/forks",
  "keys_url": "https://api.github.com/repos/mrvollger/rustybam/keys{/key_id}",
  "collaborators_url": "https://api.github.com/repos/mrvollger/rustybam/collaborators{/collaborator}",
  "teams_url": "https://api.github.com/repos/mrvollger/rustybam/teams",
  "hooks_url": "https://api.github.com/repos/mrvollger/rustybam/hooks",
  "issue_events_url": "https://api.github.com/repos/mrvollger/rustybam/issues/events{/number}",
  "events_url": "https://api.github.com/repos/mrvollger/rustybam/events",
  "assignees_url": "https://api.github.com/repos/mrvollger/rustybam/assignees{/user}",
  "branches_url": "https://api.github.com/repos/mrvollger/rustybam/branches{/branch}",
  "tags_url": "https://api.github.com/repos/mrvollger/rustybam/tags",
  "blobs_url": "https://api.github.com/repos/mrvollger/rustybam/git/blobs{/sha}",
  "git_tags_url": "https://api.github.com/repos/mrvollger/rustybam/git/tags{/sha}",
  "git_refs_url": "https://api.github.com/repos/mrvollger/rustybam/git/refs{/sha}",
  "trees_url": "https://api.github.com/repos/mrvollger/rustybam/git/trees{/sha}",
  "statuses_url": "https://api.github.com/repos/mrvollger/rustybam/statuses/{sha}",
  "languages_url": "https://api.github.com/repos/mrvollger/rustybam/languages",
  "stargazers_url": "https://api.github.com/repos/mrvollger/rustybam/stargazers",
  "contributors_url": "https://api.github.com/repos/mrvollger/rustybam/contributors",
  "subscribers_url": "https://api.github.com/repos/mrvollger/rustybam/subscribers",
  "subscription_url": "https://api.github.com/repos/mrvollger/rustybam/subscription",
  "commits_url": "https://api.github.com/repos/mrvollger/rustybam/commits{/sha}",
  "git_commits_url": "https://api.github.com/repos/mrvollger/rustybam/git/commits{/sha}",
  "comments_url": "https://api.github.com/repos/mrvollger/rustybam/comments{/number}",
  "issue_comment_url": "https://api.github.com/repos/mrvollger/rustybam/issues/comments{/number}",
  "contents_url": "https://api.github.com/repos/mrvollger/rustybam/contents/{+path}",
  "compare_url": "https://api.github.com/repos/mrvollger/rustybam/compare/{base}...{head}",
  "merges_url": "https://api.github.com/repos/mrvollger/rustybam/merges",
  "archive_url": "https://api.github.com/repos/mrvollger/rustybam/{archive_format}{/ref}",
  "downloads_url": "https://api.github.com/repos/mrvollger/rustybam/downloads",
  "issues_url": "https://api.github.com/repos/mrvollger/rustybam/issues{/number}",
  "pulls_url": "https://api.github.com/repos/mrvollger/rustybam/pulls{/number}",
  "milestones_url": "https://api.github.com/repos/mrvollger/rustybam/milestones{/number}",
  "notifications_url": "https://api.github.com/repos/mrvollger/rustybam/notifications{?since,all,participating}",
  "labels_url": "https://api.github.com/repos/mrvollger/rustybam/labels{/name}",
  "releases_url": "https://api.github.com/repos/mrvollger/rustybam/releases{/id}",
  "deployments_url": "https://api.github.com/repos/mrvollger/rustybam/deployments",
  "created_at": "2021-03-26T02:34:38Z",
  "updated_at": "2023-01-18T11:06:18Z",
  "pushed_at": "2023-01-17T19:22:07Z",
  "git_url": "git://github.com/mrvollger/rustybam.git",
  "ssh_url": "git@github.com:mrvollger/rustybam.git",
  "clone_url": "https://github.com/mrvollger/rustybam.git",
  "svn_url": "https://github.com/mrvollger/rustybam",
  "homepage": "https://mrvollger.github.io/rustybam/",
  "size": 68289,
  "stargazers_count": 19,
  "watchers_count": 19,
  "language": "Rust",
  "has_issues": true,
  "has_projects": true,
  "has_downloads": true,
  "has_wiki": true,
  "has_pages": true,
  "has_discussions": false,
  "forks_count": 1,
  "mirror_url": null,
  "archived": false,
  "disabled": false,
  "open_issues_count": 1,
  "license": null,
  "allow_forking": true,
  "is_template": false,
  "web_commit_signoff_required": false,
  "topics": [
    "bioinformatics",
    "genomics"
  ],
  "visibility": "public",
  "forks": 1,
  "open_issues": 1,
  "watchers": 19,
  "default_branch": "main",
  "permissions": {
    "admin": false,
    "maintain": false,
    "push": false,
    "triage": false,
    "pull": true
  },
  "temp_clone_token": "",
  "network_count": 1,
  "subscribers_count": 2
}