{
  "id": 73273436,
  "node_id": "MDEwOlJlcG9zaXRvcnk3MzI3MzQzNg==",
  "name": "docker-enforcer",
  "full_name": "piontec/docker-enforcer",
  "private": false,
  "owner": {
    "login": "piontec",
    "id": 1578786,
    "node_id": "MDQ6VXNlcjE1Nzg3ODY=",
    "avatar_url": "https://avatars.githubusercontent.com/u/1578786?v=4",
    "gravatar_id": "",
    "url": "https://api.github.com/users/piontec",
    "html_url": "https://github.com/piontec",
    "followers_url": "https://api.github.com/users/piontec/followers",
    "following_url": "https://api.github.com/users/piontec/following{/other_user}",
    "gists_url": "https://api.github.com/users/piontec/gists{/gist_id}",
    "starred_url": "https://api.github.com/users/piontec/starred{/owner}{/repo}",
    "subscriptions_url": "https://api.github.com/users/piontec/subscriptions",
    "organizations_url": "https://api.github.com/users/piontec/orgs",
    "repos_url": "https://api.github.com/users/piontec/repos",
    "events_url": "https://api.github.com/users/piontec/events{/privacy}",
    "received_events_url": "https://api.github.com/users/piontec/received_events",
    "type": "User",
    "site_admin": false
  },
  "html_url": "https://github.com/piontec/docker-enforcer",
  "description": "Docker enforcer - configuration compliance enforcing tool for docker",
  "fork": false,
  "url": "https://api.github.com/repos/piontec/docker-enforcer",
  "forks_url": "https://api.github.com/repos/piontec/docker-enforcer/forks",
  "keys_url": "https://api.github.com/repos/piontec/docker-enforcer/keys{/key_id}",
  "collaborators_url": "https://api.github.com/repos/piontec/docker-enforcer/collaborators{/collaborator}",
  "teams_url": "https://api.github.com/repos/piontec/docker-enforcer/teams",
  "hooks_url": "https://api.github.com/repos/piontec/docker-enforcer/hooks",
  "issue_events_url": "https://api.github.com/repos/piontec/docker-enforcer/issues/events{/number}",
  "events_url": "https://api.github.com/repos/piontec/docker-enforcer/events",
  "assignees_url": "https://api.github.com/repos/piontec/docker-enforcer/assignees{/user}",
  "branches_url": "https://api.github.com/repos/piontec/docker-enforcer/branches{/branch}",
  "tags_url": "https://api.github.com/repos/piontec/docker-enforcer/tags",
  "blobs_url": "https://api.github.com/repos/piontec/docker-enforcer/git/blobs{/sha}",
  "git_tags_url": "https://api.github.com/repos/piontec/docker-enforcer/git/tags{/sha}",
  "git_refs_url": "https://api.github.com/repos/piontec/docker-enforcer/git/refs{/sha}",
  "trees_url": "https://api.github.com/repos/piontec/docker-enforcer/git/trees{/sha}",
  "statuses_url": "https://api.github.com/repos/piontec/docker-enforcer/statuses/{sha}",
  "languages_url": "https://api.github.com/repos/piontec/docker-enforcer/languages",
  "stargazers_url": "https://api.github.com/repos/piontec/docker-enforcer/stargazers",
  "contributors_url": "https://api.github.com/repos/piontec/docker-enforcer/contributors",
  "subscribers_url": "https://api.github.com/repos/piontec/docker-enforcer/subscribers",
  "subscription_url": "https://api.github.com/repos/piontec/docker-enforcer/subscription",
  "commits_url": "https://api.github.com/repos/piontec/docker-enforcer/commits{/sha}",
  "git_commits_url": "https://api.github.com/repos/piontec/docker-enforcer/git/commits{/sha}",
  "comments_url": "https://api.github.com/repos/piontec/docker-enforcer/comments{/number}",
  "issue_comment_url": "https://api.github.com/repos/piontec/docker-enforcer/issues/comments{/number}",
  "contents_url": "https://api.github.com/repos/piontec/docker-enforcer/contents/{+path}",
  "compare_url": "https://api.github.com/repos/piontec/docker-enforcer/compare/{base}...{head}",
  "merges_url": "https://api.github.com/repos/piontec/docker-enforcer/merges",
  "archive_url": "https://api.github.com/repos/piontec/docker-enforcer/{archive_format}{/ref}",
  "downloads_url": "https://api.github.com/repos/piontec/docker-enforcer/downloads",
  "issues_url": "https://api.github.com/repos/piontec/docker-enforcer/issues{/number}",
  "pulls_url": "https://api.github.com/repos/piontec/docker-enforcer/pulls{/number}",
  "milestones_url": "https://api.github.com/repos/piontec/docker-enforcer/milestones{/number}",
  "notifications_url": "https://api.github.com/repos/piontec/docker-enforcer/notifications{?since,all,participating}",
  "labels_url": "https://api.github.com/repos/piontec/docker-enforcer/labels{/name}",
  "releases_url": "https://api.github.com/repos/piontec/docker-enforcer/releases{/id}",
  "deployments_url": "https://api.github.com/repos/piontec/docker-enforcer/deployments",
  "created_at": "2016-11-09T10:20:59Z",
  "updated_at": "2021-06-08T19:12:48Z",
  "pushed_at": "2022-12-09T05:19:15Z",
  "git_url": "git://github.com/piontec/docker-enforcer.git",
  "ssh_url": "git@github.com:piontec/docker-enforcer.git",
  "clone_url": "https://github.com/piontec/docker-enforcer.git",
  "svn_url": "https://github.com/piontec/docker-enforcer",
  "homepage": "",
  "size": 193,
  "stargazers_count": 14,
  "watchers_count": 14,
  "language": "Python",
  "has_issues": true,
  "has_projects": true,
  "has_downloads": true,
  "has_wiki": true,
  "has_pages": false,
  "has_discussions": false,
  "forks_count": 3,
  "mirror_url": null,
  "archived": false,
  "disabled": false,
  "open_issues_count": 2,
  "license": {
    "key": "gpl-3.0",
    "name": "GNU General Public License v3.0",
    "spdx_id": "GPL-3.0",
    "url": "https://api.github.com/licenses/gpl-3.0",
    "node_id": "MDc6TGljZW5zZTk="
  },
  "allow_forking": true,
  "is_template": false,
  "web_commit_signoff_required": false,
  "topics": [
    "configuration",
    "docker",
    "docker-authz-plugin",
    "docker-enforcer",
    "policy-monitoring",
    "python"
  ],
  "visibility": "public",
  "forks": 3,
  "open_issues": 2,
  "watchers": 14,
  "default_branch": "master",
  "permissions": {
    "admin": false,
    "maintain": false,
    "push": false,
    "triage": false,
    "pull": true
  },
  "temp_clone_token": "",
  "network_count": 3,
  "subscribers_count": 5
}