{
  "startTime": 1674250235487,
  "endTime": 1674250236336,
  "originalSmells": [
    {
      "rule": "apkAddUseNoCache",
      "position": {
        "lineStart": 2,
        "lineEnd": 2,
        "columnStart": 18,
        "columnEnd": 60
      }
    },
    {
      "rule": "apkAddUseNoCache",
      "position": {
        "lineStart": 9,
        "lineEnd": 9,
        "columnStart": 4,
        "columnEnd": 31
      }
    }
  ],
  "repairedSmells": [],
  "repairedDockerfile": "FROM golang:1.16-alpine AS builder\n\nRUN apk update && apk add --no-cache pkgconfig rrdtool-dev gcc libc-dev\n\nWORKDIR /build\nCOPY . .\nRUN go build -o grafana-rrd-server\n\nFROM alpine\nRUN apk add --no-cache rrdtool rrdtool-dev\nCOPY --from=builder /build/grafana-rrd-server /grafana-rrd-server\nENTRYPOINT [ \"/grafana-rrd-server\" ]"
}